MANIFEST.in
README.md
setup.py
tests/__init__.py
xtapi/__init__.py
xtapi/encoders.py
xtapi/exception_handlers.py
xtapi/exceptions.py
xtapi/main.py
xtapi/responses.py
xtapi/routing.py
xtapi/script.py
xtapi/security.py
xtapi/staticfiles.py
xtapi/templates.py
xtapi/testclient.py
xtapi.egg-info/PKG-INFO
xtapi.egg-info/SOURCES.txt
xtapi.egg-info/dependency_links.txt
xtapi.egg-info/entry_points.txt
xtapi.egg-info/not-zip-safe
xtapi.egg-info/requires.txt
xtapi.egg-info/top_level.txt
xtapi/middleware/__init__.py
xtapi/middleware/cors.py